LICENSE
MANIFEST.in
README.md
requirements.txt
setup.py
docker_registry/__init__.py
docker_registry/drivers/__init__.py
docker_registry/drivers/ufile.py
docker_registry_driver_ufile.egg-info/PKG-INFO
docker_registry_driver_ufile.egg-info/SOURCES.txt
docker_registry_driver_ufile.egg-info/dependency_links.txt
docker_registry_driver_ufile.egg-info/namespace_packages.txt
docker_registry_driver_ufile.egg-info/not-zip-safe
docker_registry_driver_ufile.egg-info/requires.txt
docker_registry_driver_ufile.egg-info/top_level.txt
tests/requirements.txt