Metadata-Version: 1.1
Name: docker-registry-driver-ufile
Version: 0.0.1
Summary: Docker registry ufile driver
Home-page: https://github.com/SkyLothar/docker-registry-driver-ufile
Author: SkyLothar
Author-email: allothar@gmail.com
License: 
